MANIFEST.in
README.rst
setup.cfg
setup.py
pypostscript/__init__.py
pypostscript/barcode.py
pypostscript/page.py
pypostscript/shapes.py
pypostscript/text.py
pypostscript.egg-info/PKG-INFO
pypostscript.egg-info/SOURCES.txt
pypostscript.egg-info/dependency_links.txt
pypostscript.egg-info/top_level.txt
pypostscript/parts_dir/barcode
pypostscript/parts_dir/page_end
pypostscript/parts_dir/page_start