Metadata-Version: 1.1
Name: pypostscript
Version: 0.1.7
Summary: Create PostScript page (including barcodes) using Python objects
Home-page: http://pypi.python.org/pypi/pypostscript
Author: Mark Henwood
Author-email: mark@mcbh.co.uk
License: MIT
Keywords: postscript printing barcode
Platform: UNKNOWN
Classifier: Development Status :: 3 - Alpha
Classifier: Environment :: Plugins
Classifier: Intended Audience :: Developers
Classifier: License :: OSI Approved :: MIT License
Classifier: Natural Language :: English
Classifier: Operating System :: OS Independent
Classifier: Programming Language :: Python :: 2.6
Classifier: Topic :: Utilities
Provides: pypostscript
